pbt/__init__.py
pbt/__version__.py
pbt/runtime.py
pbt/cli/__init__.py
pbt/cli/main.py
pbt/cli/utils.py
pbt/cli/commands/__init__.py
pbt/cli/commands/core.py
pbt/cli/commands/optimization.py
pbt/cli/commands/testing.py
pbt/core/__init__.py
pbt/core/agent_chains.py
pbt/core/comprehensive_evaluator.py
pbt/core/converter.py
pbt/core/project.py
pbt/core/prompt_chunking.py
pbt/core/prompt_evaluator.py
pbt/core/prompt_generator.py
pbt/core/prompt_optimizer.py
pbt/core/prompt_renderer.py
pbt/integrations/__init__.py
pbt/integrations/base.py
pbt/integrations/database/__init__.py
pbt/integrations/database/supabase.py
pbt/integrations/deployment/__init__.py
pbt/integrations/deployment/fly_io.py
pbt/integrations/deployment/flyio.py
pbt/integrations/deployment/render.py
pbt/integrations/import_export/__init__.py
pbt/integrations/import_export/notion.py
pbt/integrations/llm/__init__.py
pbt/integrations/llm/azure.py
pbt/integrations/llm/base.py
pbt/integrations/llm/claude.py
pbt/integrations/llm/local_models.py
pbt/integrations/llm/ollama.py
pbt/integrations/llm/openai.py
pbt/integrations/marketplace/__init__.py
pbt/integrations/marketplace/stripe.py
pbt/integrations/multimodal/__init__.py
pbt/integrations/multimodal/midjourney.py
pbt/integrations/multimodal/veo.py
pbt/integrations/multimodal/whisper.py
pbt/integrations/notification/__init__.py
pbt/integrations/notification/discord.py
pbt/integrations/notification/slack.py
pbt/integrations/vector/__init__.py
pbt/integrations/vector/pgvector.py
pbt/integrations/vector/qdrant.py
pbt/web/app.py
pbt/web/static/app.js
pbt/web/static/app_table.js
pbt/web/static/index.html
pbt/web/static/index_simple_table.html
pbt/web/static/index_table.html
pbt/web/static/styles.css
pbt/web/static/styles_table.css
pbt/web/static/table.html
pbt_cli-0.1.3.dist-info/licenses/LICENSE
pbt_cli-0.1.3.dist-info/METADATA
pbt_cli-0.1.3.dist-info/WHEEL
pbt_cli-0.1.3.dist-info/entry_points.txt
pbt_cli-0.1.3.dist-info/top_level.txt
pbt_cli-0.1.3.dist-info/RECORD
