Metadata-Version: 2.4
Name: pbt-cli
Version: 0.1.3
Summary: Infrastructure-grade prompt engineering for AI teams working across LLMs
Home-page: https://github.com/saicgr/PBT-Prompt-Build-Tool
Author-email: saipy252@gmail.com
License: MIT
Project-URL: Homepage, https://github.com/saicgr/PBT-Prompt-Build-Tool
Project-URL: Documentation, https://github.com/saicgr/PBT-Prompt-Build-Tool/blob/main/README.md
Project-URL: Repository, https://github.com/saicgr/PBT-Prompt-Build-Tool
Project-URL: Bug Tracker, https://github.com/saicgr/PBT-Prompt-Build-Tool/issues
Keywords: prompt engineering,llm,ai,machine learning,claude,openai,gpt,testing,evaluation,automation
Classifier: Development Status :: 4 - Beta
Classifier: Intended Audience :: Developers
Classifier: License :: OSI Approved :: MIT License
Classifier: Operating System :: OS Independent
Classifier: Programming Language :: Python :: 3
Classifier: Programming Language :: Python :: 3.8
Classifier: Programming Language :: Python :: 3.9
Classifier: Programming Language :: Python :: 3.10
Classifier: Programming Language :: Python :: 3.11
Classifier: Topic :: Scientific/Engineering :: Artificial Intelligence
Classifier: Topic :: Software Development :: Libraries :: Python Modules
Classifier: Topic :: Software Development :: Testing
Requires-Python: >=3.8
License-File: LICENSE
Requires-Dist: click>=8.0.0
Requires-Dist: pydantic>=2.0.0
Requires-Dist: PyYAML>=6.0
Requires-Dist: requests>=2.28.0
Requires-Dist: python-dotenv>=1.0.0
Requires-Dist: rich>=13.0.0
Requires-Dist: typer>=0.9.0
Requires-Dist: anthropic>=0.7.8
Requires-Dist: openai>=1.3.7
Requires-Dist: supabase>=2.0.2
Requires-Dist: markdownify>=0.11.6
Requires-Dist: python-jose[cryptography]>=3.3.0
Requires-Dist: passlib[bcrypt]>=1.7.4
Provides-Extra: server
Requires-Dist: fastapi>=0.104.0; extra == "server"
Requires-Dist: uvicorn[standard]>=0.24.0; extra == "server"
Requires-Dist: stripe>=7.8.0; extra == "server"
Requires-Dist: python-multipart>=0.0.6; extra == "server"
Requires-Dist: email-validator>=2.1.0; extra == "server"
Provides-Extra: dev
Requires-Dist: pytest>=7.0.0; extra == "dev"
Requires-Dist: pytest-asyncio>=0.21.0; extra == "dev"
Requires-Dist: pytest-cov>=4.0.0; extra == "dev"
Requires-Dist: black>=23.0.0; extra == "dev"
Requires-Dist: isort>=5.12.0; extra == "dev"
Requires-Dist: flake8>=6.0.0; extra == "dev"
Requires-Dist: mypy>=1.0.0; extra == "dev"
Requires-Dist: pre-commit>=3.0.0; extra == "dev"
Provides-Extra: docs
Requires-Dist: mkdocs>=1.5.0; extra == "docs"
Requires-Dist: mkdocs-material>=9.0.0; extra == "docs"
Requires-Dist: mkdocstrings[python]>=0.22.0; extra == "docs"
Provides-Extra: all
Requires-Dist: fastapi>=0.104.0; extra == "all"
Requires-Dist: uvicorn[standard]>=0.24.0; extra == "all"
Requires-Dist: stripe>=7.8.0; extra == "all"
Requires-Dist: python-multipart>=0.0.6; extra == "all"
Requires-Dist: email-validator>=2.1.0; extra == "all"
Requires-Dist: pytest>=7.0.0; extra == "all"
Requires-Dist: pytest-asyncio>=0.21.0; extra == "all"
Requires-Dist: pytest-cov>=4.0.0; extra == "all"
Requires-Dist: black>=23.0.0; extra == "all"
Requires-Dist: isort>=5.12.0; extra == "all"
Requires-Dist: flake8>=6.0.0; extra == "all"
Requires-Dist: mypy>=1.0.0; extra == "all"
Requires-Dist: mkdocs>=1.5.0; extra == "all"
Requires-Dist: mkdocs-material>=9.0.0; extra == "all"
Dynamic: home-page
Dynamic: license-file
Dynamic: requires-python
